srvresolver/__init__.py
srvresolver/postgres_resolver.py
srvresolver/srv_record.py
srvresolver/srv_resolver.py
srvresolver/srv_resolver_cached.py
srvresolver/version.py
srvresolver-0.3.5.dist-info/LICENSE
srvresolver-0.3.5.dist-info/METADATA
srvresolver-0.3.5.dist-info/WHEEL
srvresolver-0.3.5.dist-info/top_level.txt
srvresolver-0.3.5.dist-info/RECORD
