Metadata-Version: 2.1
Name: srvresolver
Version: 0.3.5
Summary: SRV record resolver for python
Home-page: https://github.com/exante/python-srvresolver
Author: EXANTE
Author-email: 
License: MIT
Keywords: dns srv resolve
Platform: UNKNOWN
Requires-Dist: dnspython
Provides-Extra: postgresql_resolver
Requires-Dist: psycopg2-binary (<2.8,>=2.7) ; extra == 'postgresql_resolver'
